crampon/__init__.py
crampon/install_environment.py
crampon-0.1.0.dist-info/METADATA
crampon-0.1.0.dist-info/WHEEL
crampon-0.1.0.dist-info/RECORD
